SocietyEvolutionNetwork/__init__.py
SocietyEvolutionNetwork/__version__.py
SocietyEvolutionNetwork/logger.py
SocietyEvolutionNetwork/network.py
SocietyEvolutionNetwork-0.1.3.dist-info/LICENSE
SocietyEvolutionNetwork-0.1.3.dist-info/METADATA
SocietyEvolutionNetwork-0.1.3.dist-info/WHEEL
SocietyEvolutionNetwork-0.1.3.dist-info/top_level.txt
SocietyEvolutionNetwork-0.1.3.dist-info/RECORD
