Metadata-Version: 2.1
Name: SocietyEvolutionNetwork
Version: 0.1.3
Summary: demo of society evolution network.
Home-page: UNKNOWN
Author: HaiLong Zheng
Author-email: SkinChange06@gmail.com
License: MIT
Platform: UNKNOWN
Classifier: License :: OSI Approved :: MIT License
Classifier: Programming Language :: Python
Classifier: Programming Language :: Python :: 3
Classifier: Programming Language :: Python :: 3.6
Classifier: Programming Language :: Python :: Implementation :: CPython
Classifier: Programming Language :: Python :: Implementation :: PyPy
Requires-Python: >=3.6.0
License-File: LICENSE
